ryang_test/test1.py
ryang_test/test2.py
ryang_test-0.0.0.2.dist-info/METADATA
ryang_test-0.0.0.2.dist-info/WHEEL
ryang_test-0.0.0.2.dist-info/top_level.txt
ryang_test-0.0.0.2.dist-info/RECORD
