Metadata-Version: 2.1
Name: ryang-test
Version: 0.0.0.2
Summary: My First Test Package
Home-page: https://blog.naver.com/hwang7531
Author: Beopryang Hwang
License: MIT
Platform: UNKNOWN
Requires-Python: >=3
